flagrs-0.1.4.dist-info/METADATA
flagrs-0.1.4.dist-info/WHEEL
flagrs/__pycache__/__init__.cpython-39.pyc
flagrs/__init__.py
flagrs/flagrs.cpython-39-x86_64-linux-gnu.so
flagrs-0.1.4.dist-info/RECORD
