Metadata-Version: 2.1
Name: flagrs
Version: 0.1.4
Summary: Rust Number Theory
Home-Page: https://gitlab.com/franksh/flagrs/
Author: Frank S. Hestvik
License: BSD-3-Clause
Project-URL: Source Code, https://gitlab.com/franksh/flagrs/
